[{"kanji": "\u77e2", "kana": "\u3084", "romaji": "Arrow"}, {"kanji": "\u5e02", "kana": "\u3057", "romaji": "City"}, {"kanji": "\u725b", "kana": "\u304e\u3085\u3046", "romaji": "Cow"}, {"kanji": "\u5207", "kana": "\u305b\u3064", "romaji": "Cut"}, {"kanji": "\u65b9", "kana": "\u307b\u3046", "romaji": "Direction"}, {"kanji": "\u6238", "kana": "\u3068", "romaji": "Door"}, {"kanji": "\u592a", "kana": "\u305f\u3044", "romaji": "Fat"}, {"kanji": "\u7236", "kana": "\u3061\u3061", "romaji": "Father"}, {"kanji": "\u5c11", "kana": "\u3057\u3087\u3046", "romaji": "Few"}, {"kanji": "\u53cb", "kana": "\u3086\u3046", "romaji": "Friend"}, {"kanji": "\u6bdb", "kana": "\u3082\u3046", "romaji": "Fur"}, {"kanji": "\u534a", "kana": "\u306f\u3093", "romaji": "Half"}, {"kanji": "\u5fc3", "kana": "\u3057\u3093", "romaji": "Heart"}, {"kanji": "\u5185", "kana": "\u306a\u3044", "romaji": "Inside"}, {"kanji": "\u751f", "kana": "\u305b\u3044", "romaji": "Life"}, {"kanji": "\u53f0", "kana": "\u3060\u3044", "romaji": "Machine"}, {"kanji": "\u6bcd", "kana": "\u306f\u306f", "romaji": "Mother"}, {"kanji": "\u5348", "kana": "\u3054", "romaji": "Noon"}, {"kanji": "\u5317", "kana": "\u307b\u304f", "romaji": "North"}, {"kanji": "\u4eca", "kana": "\u3053\u3093", "romaji": "Now"}, {"kanji": "\u53e4", "kana": "\u3053", "romaji": "Old"}, {"kanji": "\u5143", "kana": "\u3052\u3093", "romaji": "Origin"}, {"kanji": "\u5916", "kana": "\u304c\u3044", "romaji": "Outside"}, {"kanji": "\u5206", "kana": "\u3076\u3093", "romaji": "Part"}, {"kanji": "\u516c", "kana": "\u3053\u3046", "romaji": "Public"}, {"kanji": "\u5f15", "kana": "\u3072", "romaji": "Pull"}, {"kanji": "\u6b62", "kana": "\u3057", "romaji": "Stop"}, {"kanji": "\u7528", "kana": "\u3088\u3046", "romaji": "Task"}, {"kanji": "\u4e07", "kana": "\u307e\u3093", "romaji": "Ten Thousand"}, {"kanji": "\u5e83", "kana": "\u3072\u308d", "romaji": "Wide"}, {"kanji": "\u51ac", "kana": "\u3075\u3086", "romaji": "Winter"}]