[{"kanji": "\u53c8", "kana": "\u307e\u305f", "romaji": "Again"}, {"kanji": "\u7389", "kana": "\u305f\u307e", "romaji": "Ball"}, {"kanji": "\u672c", "kana": "\u307b\u3093", "romaji": "Book"}, {"kanji": "\u5b50", "kana": "\u3057", "romaji": "Child"}, {"kanji": "\u4e38", "kana": "\u307e\u308b", "romaji": "Circle"}, {"kanji": "\u6b63", "kana": "\u305b\u3044", "romaji": "Correct"}, {"kanji": "\u571f", "kana": "\u3069", "romaji": "Dirt"}, {"kanji": "\u72ac", "kana": "\u3044\u306c", "romaji": "Dog"}, {"kanji": "\u5915", "kana": "\u3086\u3046", "romaji": "Evening"}, {"kanji": "\u51fa", "kana": "\u3057\u3085\u3064", "romaji": "Exit"}, {"kanji": "\u76ee", "kana": "\u3081", "romaji": "Eye"}, {"kanji": "\u4e86", "kana": "\u308a\u3087\u3046", "romaji": "Finish"}, {"kanji": "\u706b", "kana": "\u304b", "romaji": "Fire"}, {"kanji": "\u4e94", "kana": "\u3054", "romaji": "Five"}, {"kanji": "\u56db", "kana": "\u3057", "romaji": "Four"}, {"kanji": "\u624d", "kana": "\u3055\u3044", "romaji": "Genius"}, {"kanji": "\u624b", "kana": "\u3066", "romaji": "Hand"}, {"kanji": "\u5929", "kana": "\u3066\u3093", "romaji": "Heaven"}, {"kanji": "\u738b", "kana": "\u304a\u3046", "romaji": "King"}, {"kanji": "\u5de6", "kana": "\u3055", "romaji": "Left"}, {"kanji": "\u4e2d", "kana": "\u3061\u3085\u3046", "romaji": "Middle"}, {"kanji": "\u6708", "kana": "\u3052\u3064", "romaji": "Moon"}, {"kanji": "\u3005", "kana": "\u306e\u307e", "romaji": "Repeater"}, {"kanji": "\u7530", "kana": "\u305f", "romaji": "Rice Paddy"}, {"kanji": "\u53f3", "kana": "\u3086\u3046", "romaji": "Right"}, {"kanji": "\u516d", "kana": "\u308d\u304f", "romaji": "Six"}, {"kanji": "\u5c0f", "kana": "\u3057\u3087\u3046", "romaji": "Small"}, {"kanji": "\u7acb", "kana": "\u308a\u3064", "romaji": "Stand"}, {"kanji": "\u4e01", "kana": "\u3061\u3087\u3046", "romaji": "Street"}, {"kanji": "\u65e5", "kana": "\u306b\u3061", "romaji": "Sun"}, {"kanji": "\u5200", "kana": "\u3068\u3046", "romaji": "Sword"}, {"kanji": "\u5343", "kana": "\u305b\u3093", "romaji": "Thousand"}, {"kanji": "\u6728", "kana": "\u3082\u304f", "romaji": "Tree"}, {"kanji": "\u6c34", "kana": "\u3059\u3044", "romaji": "Water"}, {"kanji": "\u767d", "kana": "\u306f\u304f", "romaji": "White"}, {"kanji": "\u6587", "kana": "\u3076\u3093", "romaji": "Writing"}, {"kanji": "\u5186", "kana": "\u3048\u3093", "romaji": "Yen"}]