[{"kanjis_kanji": "\u7686", "kanjis_kana": "\u307f\u306a", "kanjis_romaji": "All"}, {"kanjis_kanji": "\u8b1d", "kanjis_kana": "\u3057\u3083", "kanjis_romaji": "Apologize"}, {"kanjis_kanji": "\u6574", "kanjis_kana": "\u305b\u3044", "kanjis_romaji": "Arrange"}, {"kanjis_kanji": "\u6a4b", "kanjis_kana": "\u306f\u3057", "kanjis_romaji": "Bridge"}, {"kanjis_kanji": "\u9078", "kanjis_kana": "\u305b\u3093", "kanjis_romaji": "Choose"}, {"kanjis_kanji": "\u60f3", "kanjis_kana": "\u305d\u3046", "kanjis_romaji": "Concept"}, {"kanjis_kanji": "\u5668", "kanjis_kana": "\u304d", "kanjis_romaji": "Container"}, {"kanjis_kanji": "\u6697", "kanjis_kana": "\u3042\u3093", "kanjis_romaji": "Dark"}, {"kanjis_kanji": "\u7591", "kanjis_kana": "\u304e", "kanjis_romaji": "Doubt"}, {"kanjis_kanji": "\u6599", "kanjis_kana": "\u308a\u3087\u3046", "kanjis_romaji": "Fee"}, {"kanjis_kanji": "\u60c5", "kanjis_kana": "\u3058\u3087\u3046", "kanjis_romaji": "Feeling"}, {"kanjis_kanji": "\u611f", "kanjis_kana": "\u304b\u3093", "kanjis_romaji": "Feeling"}, {"kanjis_kanji": "\u69d8", "kanjis_kana": "\u3055\u307e", "kanjis_romaji": "Mr"}, {"kanjis_kanji": "\u990a", "kanjis_kana": "\u3088\u3046", "kanjis_romaji": "Foster"}, {"kanjis_kanji": "\u7dd1", "kanjis_kana": "\u307f\u3069\u308a", "kanjis_romaji": "Green"}, {"kanjis_kanji": "\u71b1", "kanjis_kana": "\u306d\u3064", "kanjis_romaji": "Heat"}, {"kanjis_kanji": "\u5104", "kanjis_kana": "\u304a\u304f", "kanjis_romaji": "Billion"}, {"kanjis_kanji": "\u6bba", "kanjis_kana": "\u3055\u3064", "kanjis_romaji": "Kill"}, {"kanjis_kanji": "\u5bbf", "kanjis_kana": "\u3057\u3085\u304f", "kanjis_romaji": "Lodge"}, {"kanjis_kanji": "\u798f", "kanjis_kana": "\u3075\u304f", "kanjis_romaji": "Luck"}, {"kanjis_kanji": "\u93e1", "kanjis_kana": "\u304b\u304c\u307f", "kanjis_romaji": "Mirror"}, {"kanjis_kanji": "\u7136", "kanjis_kana": "\u305c\u3093", "kanjis_romaji": "Nature"}, {"kanjis_kanji": "\u8a69", "kanjis_kana": "\u3057", "kanjis_romaji": "Poem"}, {"kanjis_kanji": "\u7df4", "kanjis_kana": "\u308c\u3093", "kanjis_romaji": "Practice"}, {"kanjis_kanji": "\u8cde", "kanjis_kana": "\u3057\u3087\u3046", "kanjis_romaji": "Prize"}, {"kanjis_kanji": "\u554f", "kanjis_kana": "\u3082\u3093", "kanjis_romaji": "Problem"}, {"kanjis_kanji": "\u9928", "kanjis_kana": "\u304b\u3093", "kanjis_romaji": "Building"}, {"kanjis_kanji": "\u6620", "kanjis_kana": "\u3048\u3044", "kanjis_romaji": "Reflect"}, {"kanjis_kanji": "\u9858", "kanjis_kana": "\u304c\u3093", "kanjis_romaji": "Request"}, {"kanjis_kanji": "\u58eb", "kanjis_kana": "\u3057", "kanjis_romaji": "Samurai"}, {"kanjis_kanji": "\u8ab2", "kanjis_kana": "\u304b", "kanjis_romaji": "Section"}, {"kanjis_kanji": "\u6a19", "kanjis_kana": "\u3072\u3087\u3046", "kanjis_romaji": "Signpost"}, {"kanjis_kanji": "\u9280", "kanjis_kana": "\u304e\u3093", "kanjis_romaji": "Silver"}, {"kanjis_kanji": "\u99c5", "kanjis_kana": "\u3048\u304d", "kanjis_romaji": "Station"}, {"kanjis_kanji": "\u50cf", "kanjis_kana": "\u305e\u3046", "kanjis_romaji": "Statue"}, {"kanjis_kanji": "\u984c", "kanjis_kana": "\u3060\u3044", "kanjis_romaji": "Topic"}, {"kanjis_kanji": "\u8f2a", "kanjis_kana": "\u308a\u3093", "kanjis_romaji": "Wheel"}]