[{"kanji": "\u7d00\u5143\u5f8c", "kana": "\u304d\u3052\u3093\u3054", "romaji": "AD"}, {"kanji": "\u98f2\u307f\u653e\u984c", "kana": "\u306e\u307f\u307b\u3046\u3060\u3044", "romaji": "open bar (G)"}, {"kanji": "\u98df\u3079\u653e\u984c", "kana": "\u305f\u3079\u307b\u3046\u3060\u3044", "romaji": "all-you-can-eat (G)"}, {"kanji": "\u5909\u4eba", "kana": "\u3078\u3093\u3058\u3093", "romaji": "An Eccentric"}, {"kanji": "\u5efa\u7bc9", "kana": "\u3051\u3093\u3061\u304f", "romaji": "Architecture"}, {"kanji": "\u304a\u9858\u3044", "kana": "\u304a\u306d\u304c\u3044", "romaji": "A Request"}, {"kanji": "\u8ecd", "kana": "\u3050\u3093", "romaji": "Army"}, {"kanji": "\u79cb", "kana": "\u3042\u304d", "romaji": "Autumn"}, {"kanji": "\u4e0a\u53f8", "kana": "\u3058\u3087\u3046\u3057", "romaji": "Boss"}, {"kanji": "\u5ca9", "kana": "\u3044\u308f", "romaji": "Boulder"}, {"kanji": "\u82f1\u56fd", "kana": "\u3048\u3044\u3053\u304f", "romaji": "Britain"}, {"kanji": "\u4ecf", "kana": "\u307b\u3068\u3051", "romaji": "Buddha"}, {"kanji": "\u4ecf\u6559", "kana": "\u3076\u3063\u304d\u3087\u3046", "romaji": "Buddhism"}, {"kanji": "\u8a08\u7b97", "kana": "\u3051\u3044\u3055\u3093", "romaji": "Calculation"}, {"kanji": "\u732b", "kana": "\u306d\u3053", "romaji": "Cat"}, {"kanji": "\u4e16\u7d00", "kana": "\u305b\u3044\u304d", "romaji": "Century"}, {"kanji": "\u5f0f", "kana": "\u3057\u304d", "romaji": "Ceremony"}, {"kanji": "\u5909\u5316", "kana": "\u3078\u3093\u304b", "romaji": "Change"}, {"kanji": "\u6674\u308c", "kana": "\u306f\u308c", "romaji": "Clear Weather"}, {"kanji": "\u4e0d\u5668\u7528", "kana": "\u3076\u304d\u3088\u3046", "romaji": "Clumsy"}, {"kanji": "\u81ea\u4fe1", "kana": "\u3058\u3057\u3093", "romaji": "Confidence"}, {"kanji": "\u52c7\u6c17", "kana": "\u3086\u3046\u304d", "romaji": "Courage"}, {"kanji": "\u5730\u533a", "kana": "\u3061\u304f", "romaji": "District"}, {"kanji": "\u533a", "kana": "\u304f", "romaji": "District"}, {"kanji": "\u4e0d\u4fe1", "kana": "\u3075\u3057\u3093", "romaji": "Distrust"}, {"kanji": "\u533a\u5206", "kana": "\u304f\u3076\u3093", "romaji": "Division"}, {"kanji": "\u82f1\u4f1a\u8a71", "kana": "\u3048\u3044\u304b\u3044\u308f", "romaji": "English conversation (G)"}, {"kanji": "\u82f1\u548c", "kana": "\u3048\u3044\u308f", "romaji": "English (G)"}, {"kanji": "\u82f1\u8a9e", "kana": "\u3048\u3044\u3054", "romaji": "English language (G)"}, {"kanji": "\u82f1\u6587", "kana": "\u3048\u3044\u3076\u3093", "romaji": "English (G)"}, {"kanji": "\u6bce\u6669", "kana": "\u307e\u3044\u3070\u3093", "romaji": "Every Night"}, {"kanji": "\u4fe1\u5fc3", "kana": "\u3057\u3093\u3058\u3093", "romaji": "Faith"}, {"kanji": "\u98df\u4e2d\u6bd2", "kana": "\u3057\u3087\u304f\u3061\u3085\u3046\u3069\u304f", "romaji": "Food poisoning (G)"}, {"kanji": "\u5927\u4ecf", "kana": "\u3060\u3044\u3076\u3064", "romaji": "Large Buddha (G)"}, {"kanji": "\u4eca\u6669\u306f", "kana": "\u3053\u3093\u3070\u3093\u306f", "romaji": "Good Evening"}, {"kanji": "\u6587\u6cd5", "kana": "\u3076\u3093\u307d\u3046", "romaji": "Grammar"}, {"kanji": "\u4e08", "kana": "\u305f\u3051", "romaji": "Height"}, {"kanji": "\u592b", "kana": "\u304a\u3063\u3068", "romaji": "Husband"}, {"kanji": "\u4e0d\u6cd5", "kana": "\u3075\u307b\u3046", "romaji": "Illegal"}, {"kanji": "\u4e8b\u5909", "kana": "\u3058\u3078\u3093", "romaji": "Incident"}, {"kanji": "\u4f1d", "kana": "\u3064\u3066", "romaji": "Intermediary"}, {"kanji": "\u5b50\u732b", "kana": "\u3053\u306d\u3053", "romaji": "Kitten"}, {"kanji": "\u6628\u5e74", "kana": "\u3055\u304f\u306d\u3093", "romaji": "Last Year"}, {"kanji": "\u5217", "kana": "\u308c\u3064", "romaji": "Line"}, {"kanji": "\u663c\u4f11\u307f", "kana": "\u3072\u308b\u3084\u3059\u307f", "romaji": "Lunch Break"}, {"kanji": "\u3054\u98ef", "kana": "\u3054\u306f\u3093", "romaji": "Meal"}, {"kanji": "\u98ef", "kana": "\u3081\u3057", "romaji": "Meal"}, {"kanji": "\u65b9\u6cd5", "kana": "\u307b\u3046\u307b\u3046", "romaji": "Method"}, {"kanji": "\u60c5\u3051\u306a\u3044", "kana": "\u306a\u3055\u3051\u306a\u3044", "romaji": "Miserable"}, {"kanji": "\u6620\u753b\u9928", "kana": "\u3048\u3044\u304c\u304b\u3093", "romaji": "Movie Theater"}, {"kanji": "\u4eba\u6bba\u3057", "kana": "\u3072\u3068\u3054\u308d\u3057", "romaji": "Murder"}, {"kanji": "\u6bba\u4eba\u8005", "kana": "\u3055\u3064\u3058\u3093\u3057\u3083", "romaji": "Murderer"}, {"kanji": "\u6d77\u8ecd", "kana": "\u304b\u3044\u3050\u3093", "romaji": "Navy"}, {"kanji": "\u65b0\u7bc9", "kana": "\u3057\u3093\u3061\u304f", "romaji": "Newly Built"}, {"kanji": "\u6669", "kana": "\u3070\u3093", "romaji": "Night"}, {"kanji": "\u663c", "kana": "\u3072\u308b", "romaji": "Noon"}, {"kanji": "\u8a08\u753b", "kana": "\u3051\u3044\u304b\u304f", "romaji": "Plan"}, {"kanji": "\u6bd2", "kana": "\u3069\u304f", "romaji": "Poison"}, {"kanji": "\u6bd2\u30ac\u30b9", "kana": "\u3069\u304f\u304c\u3059", "romaji": "Poison Gas"}, {"kanji": "\u4e2d\u6bd2", "kana": "\u3061\u3085\u3046\u3069\u304f", "romaji": "Poisoning"}, {"kanji": "\u6709\u6bd2", "kana": "\u3086\u3046\u3069\u304f", "romaji": "Poisonous"}, {"kanji": "\u8fd4\u4fe1", "kana": "\u3078\u3093\u3057\u3093", "romaji": "Reply"}, {"kanji": "\u6307\u8f2a", "kana": "\u3086\u3073\u308f", "romaji": "Ring"}, {"kanji": "\u8f2a\u30b4\u30e0", "kana": "\u308f\u3054\u3080", "romaji": "Rubber Band"}, {"kanji": "\u5927\u5909", "kana": "\u305f\u3044\u3078\u3093", "romaji": "Serious"}, {"kanji": "\u6d45\u3044", "kana": "\u3042\u3055\u3044", "romaji": "Shallow"}, {"kanji": "\u5358\u306b", "kana": "\u305f\u3093\u306b", "romaji": "Simply"}, {"kanji": "\u5742", "kana": "\u3055\u304b", "romaji": "Slope"}, {"kanji": "\u8ecd\u4eba", "kana": "\u3050\u3093\u3058\u3093", "romaji": "Soldier"}, {"kanji": "\u9811\u4e08", "kana": "\u304c\u3093\u3058\u3087\u3046", "romaji": "Solid"}, {"kanji": "\u6625", "kana": "\u306f\u308b", "romaji": "Spring"}, {"kanji": "\u6625\u4f11\u307f", "kana": "\u306f\u308b\u3084\u3059\u307f", "romaji": "Spring Break"}, {"kanji": "\u5909", "kana": "\u3078\u3093", "romaji": "Strange"}, {"kanji": "\u5909\u4e8b", "kana": "\u3078\u3093\u3058", "romaji": "Misconduct (G)"}, {"kanji": "\u4e08\u592b", "kana": "\u3058\u3087\u3046\u3076", "romaji": "Sturdy"}, {"kanji": "\u540c\u671f\u4e2d", "kana": "\u3069\u3046\u304d\u3061\u3085\u3046", "romaji": "Syncing"}, {"kanji": "\u7f8e\u5473\u3057\u3044", "kana": "\u304a\u3044\u3057\u3044", "romaji": "Tasty"}, {"kanji": "\u5bfa", "kana": "\u3066\u3089", "romaji": "Temple"}, {"kanji": "\u6628\u4eca", "kana": "\u3055\u3063\u3053\u3093", "romaji": "These Days"}, {"kanji": "\u6574\u7406\u3059\u308b", "kana": "\u305b\u3044\u308a\u3059\u308b", "romaji": "To Arrange"}, {"kanji": "\u6574\u3048\u308b", "kana": "\u3068\u3068\u306e\u3048\u308b", "romaji": "To Arrange"}, {"kanji": "\u597d\u3080", "kana": "\u3053\u306e\u3080", "romaji": "To Be Fond Of"}, {"kanji": "\u4fe1\u3058\u308b", "kana": "\u3057\u3093\u3058\u308b", "romaji": "To Believe"}, {"kanji": "\u5efa\u3066\u308b", "kana": "\u305f\u3066\u308b", "romaji": "To Build"}, {"kanji": "\u5909\u3048\u308b", "kana": "\u304b\u3048\u308b", "romaji": "To Change"}, {"kanji": "\u6674\u308c\u308b", "kana": "\u306f\u308c\u308b", "romaji": "To Clear Up"}, {"kanji": "\u6ce3\u304f", "kana": "\u306a\u304f", "romaji": "To Cry"}, {"kanji": "\u653e\u3064", "kana": "\u306f\u306a\u3064", "romaji": "To Fire"}, {"kanji": "\u898b\u8fd4\u3059", "kana": "\u307f\u304b\u3048\u3059", "romaji": "Revenge (G)"}, {"kanji": "\u6697\u8a18\u3059\u308b", "kana": "\u3042\u3093\u304d\u3059\u308b", "romaji": "To Memorize"}, {"kanji": "\u7df4\u7fd2\u3059\u308b", "kana": "\u308c\u3093\u3057\u3085\u3046\u3059\u308b", "romaji": "To Practice"}, {"kanji": "\u6620\u3059", "kana": "\u3046\u3064\u3059", "romaji": "To Project"}, {"kanji": "\u5e30\u308b", "kana": "\u304b\u3048\u308b", "romaji": "Return (G)"}, {"kanji": "\u5408\u8a08", "kana": "\u3054\u3046\u3051\u3044", "romaji": "Total"}, {"kanji": "\u4fe1\u53f7", "kana": "\u3057\u3093\u3054\u3046", "romaji": "Traffic Light"}, {"kanji": "\u4fe1\u7528", "kana": "\u3057\u3093\u3088\u3046", "romaji": "Trust"}, {"kanji": "\u5909\u6b7b", "kana": "\u3078\u3093\u3057", "romaji": "Strange death (G)"}, {"kanji": "\u6642\u8a08", "kana": "\u3068\u3051\u3044", "romaji": "Watch"}, {"kanji": "\u5358\u8a9e", "kana": "\u305f\u3093\u3054", "romaji": "Word"}, {"kanji": "\u6628\u65e5", "kana": "\u304d\u306e\u3046", "romaji": "Yesterday"}]